euvdmapper/__init__.py
euvdmapper/cli.py
euvdmapper/euvd_alert.py
euvdmapper/fetch_api.py
euvdmapper-1.7.dist-info/licenses/LICENSE
euvdmapper-1.7.dist-info/METADATA
euvdmapper-1.7.dist-info/WHEEL
euvdmapper-1.7.dist-info/entry_points.txt
euvdmapper-1.7.dist-info/top_level.txt
euvdmapper-1.7.dist-info/RECORD
