Metadata-Version: 2.4
Name: euvdmapper
Version: 1.7
Summary: ENISA EUVD data fetcher and formatter
Author-email: Ferdi Gül <0xfrd1gul@gmail.com>
License-Expression: MIT
Project-URL: Homepage, https://github.com/FerdiGul/euvdmapper
Project-URL: Repository, https://github.com/FerdiGul/euvdmapper
Project-URL: Issues, https://github.com/FerdiGul/euvdmapper/issues
Project-URL: LinkedIn, https://www.linkedin.com/in/gulferdi/
Requires-Python: >=3.7
License-File: LICENSE
Requires-Dist: httpx>=0.23.0
Requires-Dist: pyyaml>=6.0
Dynamic: license-file
